CHANGES.rst
LICENSE
postal_address/__init__.py
postal_address/__version__.py
postal_address/address.py
postal_address/territory.py
postal_address/tests/__init__.py
postal_address/tests/test_address.py
postal_address/tests/test_territory.py
postal_address-22.4.22.1.dist-info/LICENSE
postal_address-22.4.22.1.dist-info/WHEEL
postal_address-22.4.22.1.dist-info/METADATA
postal_address-22.4.22.1.dist-info/RECORD
